jupyter_whitelist_env/__init__.py
jupyter_whitelist_env-0.1.1.dist-info/LICENSE
jupyter_whitelist_env-0.1.1.dist-info/WHEEL
jupyter_whitelist_env-0.1.1.dist-info/METADATA
jupyter_whitelist_env-0.1.1.dist-info/RECORD
