Metadata-Version: 2.1
Name: jupyter-whitelist-env
Version: 0.1.1
Summary: 
License: MIT
Author: Daisuke Taniwaki
Author-email: daisuketaniwaki@gmail.com
Requires-Python: >=3.7,<4.0
Classifier: License :: OSI Approved :: MIT License
Classifier: Programming Language :: Python :: 3
Classifier: Programming Language :: Python :: 3.7
Classifier: Programming Language :: Python :: 3.8
Requires-Dist: notebook (>=6.0,<7.0)
